examples/__init__.py
examples/retrieve_certificate.py
examples/retrieve_company_keys.py
examples/retrieve_key.py
examples/retrieve_secrets.py
examples/send_certificate_ed25519.py
examples/send_certificate_raw.py
examples/send_key_create.py
examples/send_key_revoke.py
examples/send_key_rotate.py
examples/send_secret_nacl_box.py
examples/common/__init__.py
examples/common/log.py
examples/common/settings.py
katena_chain_sdk_py/__init__.py
katena_chain_sdk_py/transactor.py
katena_chain_sdk_py/api/__init__.py
katena_chain_sdk_py/api/client.py
katena_chain_sdk_py/api/handler.py
katena_chain_sdk_py/crypto/__init__.py
katena_chain_sdk_py/crypto/base_key.py
katena_chain_sdk_py/crypto/ed25519/__init__.py
katena_chain_sdk_py/crypto/ed25519/private_key.py
katena_chain_sdk_py/crypto/ed25519/public_key.py
katena_chain_sdk_py/crypto/nacl/__init__.py
katena_chain_sdk_py/crypto/nacl/private_key.py
katena_chain_sdk_py/crypto/nacl/public_key.py
katena_chain_sdk_py/entity/__init__.py
katena_chain_sdk_py/entity/tx.py
katena_chain_sdk_py/entity/tx_data.py
katena_chain_sdk_py/entity/tx_data_interface.py
katena_chain_sdk_py/entity/tx_data_state.py
katena_chain_sdk_py/entity/tx_signer.py
katena_chain_sdk_py/entity/account/__init__.py
katena_chain_sdk_py/entity/account/common.py
katena_chain_sdk_py/entity/account/keys.py
katena_chain_sdk_py/entity/api/__init__.py
katena_chain_sdk_py/entity/api/raw_response.py
katena_chain_sdk_py/entity/api/tx_result.py
katena_chain_sdk_py/entity/certify/__init__.py
katena_chain_sdk_py/entity/certify/certificate.py
katena_chain_sdk_py/entity/certify/common.py
katena_chain_sdk_py/entity/certify/secret.py
katena_chain_sdk_py/exceptions/__init__.py
katena_chain_sdk_py/exceptions/api_exception.py
katena_chain_sdk_py/exceptions/client_exception.py
katena_chain_sdk_py/serializer/__init__.py
katena_chain_sdk_py/serializer/base_schema.py
katena_chain_sdk_py/serializer/bytes_field.py
katena_chain_sdk_py/serializer/crypto_field.py
katena_chain_sdk_py-1.3.0.dist-info/LICENSE
katena_chain_sdk_py-1.3.0.dist-info/METADATA
katena_chain_sdk_py-1.3.0.dist-info/WHEEL
katena_chain_sdk_py-1.3.0.dist-info/top_level.txt
katena_chain_sdk_py-1.3.0.dist-info/RECORD
