Metadata-Version: 2.1
Name: katena-chain-sdk-py
Version: 1.3.0
Summary: A SDK client for Katena Chain by Transchain
Home-page: https://github.com/katena-chain/sdk-py
Author: Transchain
Author-email: devops@transchain.fr
License: Apache-2.0
Platform: UNKNOWN
Classifier: License :: OSI Approved :: Apache Software License
Classifier: Programming Language :: Python :: 3
Classifier: Programming Language :: Python :: 3.6
Classifier: Programming Language :: Python :: 3.8
Requires-Dist: marshmallow (==3.2.1)
Requires-Dist: pynacl (==1.3.0)
Requires-Dist: requests (==2.22.0)
